test/__init__.py
test/test_background_noise_estimation.py
test/test_completeness.py
test/test_pmf_detection-deprecated.py
test/test_pmf_detector.py
trex_flare_detector-0.1.0.dist-info/METADATA
trex_flare_detector-0.1.0.dist-info/WHEEL
trex_flare_detector-0.1.0.dist-info/top_level.txt
trex_flare_detector-0.1.0.dist-info/RECORD
